{
  "Spase": {
    "xmlns": "http://www.spase-group.org/data/schema",
    "Version": "2.2.2",
    "DisplayData": {
      "ResourceID": "spase://VSPO/DisplayData/AIM/SOFIE/PT90M",
      "ResourceHeader": {
        "ResourceName": "AIM/SOFIE daily plots, parameters vs.alt. & long., etc. (L3 Summary data)",
        "ReleaseDate": "2019-03-21T10:23:00",
        "Description": "This SOFIE (Solar Occultation for Ice Experiment) data set contains color-coded pairs of\ndaily plots of several physical parameters vs altitude and longitude.  \nParameters include temperature, mixing ratios for H2O, O3 and CH4, and \nice mass.  Members of each pair are for the northern and southern\nhemispheres.  The interface also supports plotting of lower level\ndata.",
        "Contact": {
          "PersonID": "spase://SMWG/Person/Mark.Hervig",
          "Role": "GeneralContact"
        },
        "InformationURL": {
          "Name": "Info interface page at Hampton U.",
          "URL": "http://aim.hamptonu.edu/instrmt/sofie.html"
        },
        "PriorID": "spase://VSPO/DisplayData/AIM/SOFIE/L3_Data"
      },
      "AccessInformation": {
        "RepositoryID": "spase://SMWG/Repository/GATS",
        "Availability": "Online",
        "AccessRights": "Open",
        "AccessURL": {
          "Name": "Data interface page at GATS, Inc.",
          "URL": "http://sofie.gats-inc.com/sofie/index.php"
        },
        "Format": "NetCDF"
      },
      "InstrumentID": "spase://SMWG/Instrument/AIM/SOFIE",
      "MeasurementType": "Profile",
      "TemporalDescription": {
        "TimeSpan": {
          "StartDate": "2007-05-28T00:00:00",
          "RelativeStopDate": "-P2M"
        },
        "Cadence": "PT90M"
      },
      "ObservedRegion": "Earth.NearSurface"
    }
  }
}