{
  "Spase": {
    "xmlns": "http://www.spase-group.org/data/schema",
    "xmlns:xsi": "http://www.w3.org/2001/XMLSchema-instance",
    "xsi:schemaLocation": "http://www.spase-group.org/data/schema  http://www.spase-group.org/data/schema/spase-2_6_0.xsd",
    "Version": "2.6.0",
    "NumericalData": {
      "ResourceID": "spase://NASA/NumericalData/Wind/3DP/ECHSFITS_E0-YR/PT96S",
      "ResourceHeader": {
        "ResourceName": "Wind 3DP Electron Core Halo Strahl Moments, 96s, year files",
        "DOI": "https://doi.org/10.48322/rgf7-3h67",
        "ReleaseDate": "2023-04-25T09:07:24",
        "Description": "These ~96s electron core halo and strahl parameters are moments of Wind 3DP EESA-L and EESA-H measurements, corrected for spacecraft potential and other instrumental effects.",
        "Acknowledgement": "Chadi S. Salem and Marc Pulupa",
        "PublicationInfo": {
          "Title": "Wind 3DP Electron Core Halo Strahl Moments, 96 s, year files",
          "Authors": "Salem, Chadi S.; Pulupa, Marc",
          "PublicationDate": "2023-04-27T00:00:00",
          "PublishedBy": "NASA Space Physics Data Facility"
        },
        "Contact": [
          {
            "PersonID": "spase://SMWG/Person/Chadi.S.Salem",
            "Role": "PrincipalInvestigator"
          },
          {
            "PersonID": "spase://SMWG/Person/Scott.Boardsen",
            "Role": "MetadataContact"
          },
          {
            "PersonID": "spase://SMWG/Person/Robert.M.Candey",
            "Role": "MetadataContact"
          }
        ],
        "InformationURL": [
          {
            "Name": "Reference",
            "URL": "https://arxiv.org/abs/2107.08125",
            "Description": "Salem, C. S., et al., Precision Electron Measurements in the Solar Wind at 1AU from NASA’s Wind spacecraft, Astron. & Astrophys. Note paper has been accepted in 2023"
          },
          {
            "Name": "Reference",
            "URL": "https://doi.org/10.1002/2013JA019359",
            "Description": "Pulupa, M., et al., Spin-modulated spacecraft floating potential: Observations and effects on electron moments, J. Geophys. Res. Space Physics, Vol. 119, 647-657, doi:10.1002/2013JA019359"
          },
          {
            "Name": "Reference",
            "URL": "https://doi.org/10.1007/BF00751328",
            "Description": "Lin, R. P. et al., A Three-dimensional plasma and energetic particle investigation for the Wind spacecraft, Space Science Reviews, Vol. 71, p125-153, 1995."
          }
        ]
      },
      "AccessInformation": [
        {
          "RepositoryID": "spase://SMWG/Repository/NASA/GSFC/SPDF",
          "Availability": "Online",
          "AccessRights": "Open",
          "AccessURL": {
            "Name": "HTTPS from SPDF",
            "URL": "https://spdf.gsfc.nasa.gov/pub/data/wind/3dp/3dp_echsfits_e0-yr/",
            "ProductKey": "WIND_3DP_ECHSFITS_E0-YR",
            "Description": "In CDF via HTTP from SPDF"
          },
          "Format": "CDF",
          "Acknowledgement": "Please acknowledge the CDAWeb team at GSFC/SPDF."
        },
        {
          "RepositoryID": "spase://SMWG/Repository/NASA/GSFC/SPDF",
          "Availability": "Online",
          "AccessRights": "Open",
          "AccessURL": {
            "Name": "CDAWeb",
            "URL": "https://cdaweb.gsfc.nasa.gov/cgi-bin/eval2.cgi?dataset=WIND_3DP_ECHSFITS_E0-YR&index=sp_phys",
            "ProductKey": "WIND_3DP_ECHSFITS_E0-YR",
            "Description": "In CDF via HTTP from SPDF: Online plotting and data listing"
          },
          "Format": "Text",
          "Acknowledgement": "Please acknowledge the CDAWeb team at GSFC/SPDF"
        },
        {
          "RepositoryID": "spase://SMWG/Repository/NASA/GSFC/SPDF",
          "Availability": "Online",
          "AccessRights": "Open",
          "AccessURL": {
            "Name": "HAPI",
            "URL": "https://cdaweb.gsfc.nasa.gov/hapi",
            "ProductKey": "WIND_3DP_ECHSFITS_E0-YR",
            "Description": "Web Service to this product using the HAPI interface."
          },
          "Format": "CSV",
          "Acknowledgement": "Please acknowledge the CDAWeb team at GSFC/SPDF."
        }
      ],
      "MeasurementType": "EnergeticParticles"
    }
  }
}