{
  "Spase": {
    "xmlns:xsi": "http://www.w3.org/2001/XMLSchema-instance",
    "xmlns": "http://www.spase-group.org/data/schema",
    "xsi:schemaLocation": "http://www.spase-group.org/data/schema http://www.spase-group.org/data/schema/spase-2_0_1.xsd",
    "Version": "2.0.1",
    "NumericalData": {
      "ResourceID": "spase://VMO/NumericalData/ST5-224/MAG/v1_PT01S",
      "ResourceHeader": {
        "ResourceName": "ST5-224 MAG Data",
        "ReleaseDate": "2010-03-12T12:34:56.789",
        "Description": "Magnetic field and position data from the ST5-224 satellite. Calibrated science quality data.",
        "Acknowledgement": "User will acknowledge the ST5 magnetometer team in any publication resulting from the use of these data.",
        "Contact": {
          "PersonID": "spase://SMWG/Person/Guan.Le",
          "Role": "PrincipalInvestigator"
        }
      },
      "AccessInformation": {
        "RepositoryID": "spase://SMWG/Repository/NASA/GSFC/VHO-VMO",
        "Availability": "Online",
        "AccessRights": "Open",
        "AccessURL": {
          "Name": "Download of ST5 magnetic field data",
          "URL": "http://vmo.nasa.gov/mission/st5",
          "Description": "Repository of the ST5 data"
        },
        "Format": "Text",
        "Encoding": "GZIP"
      },
      "ProviderResourceName": "ST5 MAG Data",
      "ProviderProcessingLevel": "Level 2",
      "ProviderVersion": "1",
      "InstrumentID": "spase://SMWG/Instrument/ST5-224/MAG",
      "MeasurementType": [
        "Ephemeris",
        "MagneticField"
      ],
      "TemporalDescription": {
        "TimeSpan": {
          "StartDate": "2006-03-26T20:37:22",
          "StopDate": "2006-06-19T23:59:58"
        }
      },
      "ObservedRegion": "Earth.Magnetosphere.Main",
      "Keyword": "Magnetic field",
      "Parameter": [
        {
          "Name": "Year",
          "ParameterKey": "Field 1",
          "Description": "Year of the observation",
          "Cadence": "PT01S",
          "Structure": "\n         ",
          "Support": {
            "SupportQuantity": "Temporal"
          }
        },
        {
          "Name": "Month",
          "ParameterKey": "Field 2",
          "Description": "Month of year of the observation",
          "Cadence": "PT01S",
          "Structure": "\n         ",
          "Support": {
            "SupportQuantity": "Temporal"
          }
        },
        {
          "Name": "Day",
          "ParameterKey": "Field 3",
          "Description": "Day of month of the observation",
          "Cadence": "PT01S",
          "Structure": "\n         ",
          "Support": {
            "SupportQuantity": "Temporal"
          }
        },
        {
          "Name": "Hour",
          "ParameterKey": "Field 4",
          "Description": "Hour of the observation",
          "Cadence": "PT01S",
          "Structure": "\n         ",
          "Support": {
            "SupportQuantity": "Temporal"
          }
        },
        {
          "Name": "Minute",
          "ParameterKey": "Field 5",
          "Description": "Minute of the observation",
          "Cadence": "PT01S",
          "Structure": "\n         ",
          "Support": {
            "SupportQuantity": "Temporal"
          }
        },
        {
          "Name": "Second",
          "ParameterKey": "Field 6",
          "Description": "Second of the observation",
          "Cadence": "PT01S",
          "Structure": "\n         ",
          "Support": {
            "SupportQuantity": "Temporal"
          }
        },
        {
          "Name": "Bx",
          "ParameterKey": "Field 7",
          "Description": "Bx magnetic field component in SM coordinates.",
          "Cadence": "PT01S",
          "Units": "nT",
          "UnitsConversion": "1.0e-9>T",
          "CoordinateSystem": {
            "CoordinateRepresentation": "Cartesian",
            "CoordinateSystemName": "SM"
          },
          "Field": {
            "Qualifier": "Component.I",
            "FieldQuantity": "Magnetic"
          }
        },
        {
          "Name": "By",
          "ParameterKey": "Field 8",
          "Description": "By magnetic field component in SM coordinates.",
          "Cadence": "PT01S",
          "Units": "nT",
          "UnitsConversion": "1.0e-9>T",
          "CoordinateSystem": {
            "CoordinateRepresentation": "Cartesian",
            "CoordinateSystemName": "SM"
          },
          "Field": {
            "Qualifier": "Component.J",
            "FieldQuantity": "Magnetic"
          }
        },
        {
          "Name": "Bz",
          "ParameterKey": "Field 9",
          "Description": "Bz magnetic field component in SM coordinates.",
          "Cadence": "PT01S",
          "Units": "nT",
          "UnitsConversion": "1.0e-9>T",
          "CoordinateSystem": {
            "CoordinateRepresentation": "Cartesian",
            "CoordinateSystemName": "SM"
          },
          "Field": {
            "Qualifier": "Component.K",
            "FieldQuantity": "Magnetic"
          }
        },
        {
          "Name": "IGRF Bx",
          "ParameterKey": "Field 10",
          "Description": "IGRF model Bx magnetic field component in SM coordinates.",
          "Caveats": "This parameter is calculated using the IGRF model.",
          "Cadence": "PT01S",
          "Units": "nT",
          "UnitsConversion": "1.0e-9>T",
          "CoordinateSystem": {
            "CoordinateRepresentation": "Cartesian",
            "CoordinateSystemName": "SM"
          },
          "Field": {
            "Qualifier": "Component.I",
            "FieldQuantity": "Magnetic"
          }
        },
        {
          "Name": "IGRF By",
          "ParameterKey": "Field 11",
          "Description": "IGRF model By magnetic field component in SM coordinates.",
          "Caveats": "This parameter is calculated using the IGRF model.",
          "Cadence": "PT01S",
          "Units": "nT",
          "UnitsConversion": "1.0e-9>T",
          "CoordinateSystem": {
            "CoordinateRepresentation": "Cartesian",
            "CoordinateSystemName": "SM"
          },
          "Field": {
            "Qualifier": "Component.J",
            "FieldQuantity": "Magnetic"
          }
        },
        {
          "Name": "IGRF Bz",
          "ParameterKey": "Field 12",
          "Description": "IGRF model Bz magnetic field component in SM coordinates.",
          "Caveats": "This parameter is calculated using the IGRF model.",
          "Cadence": "PT01S",
          "Units": "nT",
          "UnitsConversion": "1.0e-9>T",
          "CoordinateSystem": {
            "CoordinateRepresentation": "Cartesian",
            "CoordinateSystemName": "SM"
          },
          "Field": {
            "Qualifier": "Component.K",
            "FieldQuantity": "Magnetic"
          }
        },
        {
          "Name": "X",
          "ParameterKey": "Field 13",
          "Description": "The X component of satellite's position in SM coordinates",
          "Cadence": "PT01S",
          "Units": "Re",
          "UnitsConversion": "6.3712e6>m",
          "CoordinateSystem": {
            "CoordinateRepresentation": "Cartesian",
            "CoordinateSystemName": "SM"
          },
          "Structure": {
            "Element": {
              "Name": "X",
              "Qualifier": "Component.I",
              "Index": "1"
            }
          },
          "Support": {
            "SupportQuantity": "Positional"
          }
        },
        {
          "Name": "Y",
          "ParameterKey": "Field 14",
          "Description": "The Y component of satellite's position in SM coordinates",
          "Cadence": "PT01S",
          "Units": "Re",
          "UnitsConversion": "6.3712e6>m",
          "CoordinateSystem": {
            "CoordinateRepresentation": "Cartesian",
            "CoordinateSystemName": "SM"
          },
          "Structure": {
            "Element": {
              "Name": "Y",
              "Qualifier": "Component.J",
              "Index": "2"
            }
          },
          "Support": {
            "SupportQuantity": "Positional"
          }
        },
        {
          "Name": "Z",
          "ParameterKey": "Field 15",
          "Description": "The Z component of satellite's position in SM coordinates",
          "Cadence": "PT01S",
          "Units": "Re",
          "UnitsConversion": "6.3712e6>m",
          "CoordinateSystem": {
            "CoordinateRepresentation": "Cartesian",
            "CoordinateSystemName": "SM"
          },
          "Structure": {
            "Element": {
              "Name": "Z",
              "Qualifier": "Component.K",
              "Index": "1"
            }
          },
          "Support": {
            "SupportQuantity": "Positional"
          }
        }
      ]
    }
  }
}