{
  "Spase": {
    "xmlns": "http://www.spase-group.org/data/schema",
    "Version": "2.2.0",
    "Person": {
      "ResourceID": "spase://SMWG/Person/Gerardo.Cifuentes.Nava",
      "ReleaseDate": "2010-08-05T17:35:46Z",
      "PersonName": "Gerardo Cifuentes Nava",
      "OrganizationName": "Instituto de Geofisica",
      "Address": "Instituto de Geofisica, Ciudad Universitaria, Delegacion de Coyoacan, Codigo 04510 Mexico D.F., Mexico",
      "Email": "gercifue@igeofcu.unam.mx",
      "PhoneNumber": "+52 5 62 41 49"
    }
  }
}