{
  "Spase": {
    "xmlns:xsi": "http://www.w3.org/2001/XMLSchema-instance",
    "xmlns": "http://www.spase-group.org/data/schema",
    "xsi:schemaLocation": "http://www.spase-group.org/data/schema http://www.spase-group.org/data/schema/spase-2_2_0.xsd",
    "Version": "2.2.0",
    "Person": {
      "ResourceID": "spase://SMWG/Person/Ivan.A.Galkin",
      "ReleaseDate": "2010-08-05T17:35:46Z",
      "PersonName": "Dr. Ivan A. Galkin",
      "OrganizationName": "University of Massachusetts Lowell, Center for Atmospheric Research",
      "Address": "600 Suffolk Street, Lowell, MA 01851 U.S.A.>",
      "Email": "Ivan_Galkin@uml.edu",
      "PhoneNumber": "978-934-4912"
    }
  }
}