{
  "Spase": {
    "xmlns:xsi": "http://www.w3.org/2001/XMLSchema-instance",
    "xmlns": "http://www.spase-group.org/data/schema",
    "xsi:schemaLocation": "http://www.spase-group.org/data/schema http://www.spase-group.org/data/schema/spase-2_2_2.xsd",
    "Version": "2.2.2",
    "Person": {
      "ResourceID": "spase://SMWG/Person/Muhammad.Rafiq",
      "ReleaseDate": "2012-04-20T12:34:56.789",
      "PersonName": "Muhammad Rafiq",
      "OrganizationName": "Pakistan Meteorological Department, Geophysical Centre",
      "Address": "Geophysical Centre, Pakistan Meteorological Department, Brewery Road P. O. Box 2, Quetta, Pakistan",
      "Email": "metq@qta.paknet.com.pk",
      "FaxNumber": "092 081 853032"
    }
  }
}