{
  "Spase": {
    "xmlns": "http://www.spase-group.org/data/schema",
    "xmlns:xsi": "http://www.w3.org/2001/XMLSchema-instance",
    "xsi:schemaLocation": "http://www.spase-group.org/data/schema https://www.spase-group.org/data/schema/spase-2_5_0.xsd",
    "Version": "2.5.0",
    "Person": {
      "ResourceID": "spase://IUGONET/Person/Tomoaki.Hori",
      "ReleaseDate": "2011-04-01T00:00:00",
      "PersonName": "Tomoaki Hori",
      "OrganizationName": "Institute for Space and Earth Environmental Research, Nagoya University",
      "Email": "horit (at) isee.nagoya-u.ac.jp"
    }
  }
}