<?xml version="1.0" encoding="UTF-8"?>
<Spase xmlns="http://www.spase-group.org/data/schema" xmlns:xsi="http://www.w3.org/2001/XMLSchema-instance" xsi:schemaLocation="http://www.spase-group.org/data/schema  https://www.spase-group.org/data/schema/spase-2_3_2.xsd">
  <Version>2.3.2</Version>
  <NumericalData>
    <ResourceID>spase://NASA/NumericalData/POLAR/PWI/MCA/PT1.3S</ResourceID>
    <ResourceHeader>
      <ResourceName>Polar Plasma Wave Instrument (PWI), Multichannel Analyzer - 1.3 sec resolution fields</ResourceName>
      <AlternateName>PO_H0_PWI</AlternateName>
      <AlternateName>Polar PWI MCA CDFs at NASA's CDAWeb</AlternateName>
      <ReleaseDate>2021-04-27T15:38:11Z</ReleaseDate>
      <Description>The PO_H0_PWI Multichannel Analyzer (MCA) CDF files provide good time resolution with relatively poor frequency resolution. An electric field measurement covers 5.6 Hz to 311 kHz in 20 channels logarithmically spaced. The magnetic field measurements cover a range from 5.6 Hz to 10 kHz in 14 channels logarithmically spaced. Reference: Gurnett, D.A. et al, The Polar plasma wave instrument, Space Science Reviews, Vol. 71, pp. 597-622, 1995. Note: The electron cyclotron frequencies are derived from the following: Fce = 0.028 kHz*B, where B is the magnitude of the ambient magnetic field measured in nT.</Description>
      <Acknowledgement>Users please acknowledge the Coordinated Data Analysis Web (CDAWeb) at the NASA Goddard Space Flight Center and Polar PWI instrument Principal Investigator Don Gurnett.</Acknowledgement>
      <Contact>
        <PersonID>spase://SMWG/Person/Donald.A.Gurnett</PersonID>
        <Role>PrincipalInvestigator</Role>
      </Contact>
      <Contact>
        <PersonID>spase://SMWG/Person/J.Douglas.Menietti</PersonID>
        <Role>GeneralContact</Role>
      </Contact>
      <InformationURL>
        <Name>Polar Plasma Wave Investigation (PWI) Data and User's Guides</Name>
        <URL>http://www-pw.physics.uiowa.edu/plasma-wave/istp/polar/data.html</URL>
        <Description>A Polar PWI page is maintained at the University of Iowa with descriptions of interpretation issues, user's guides, data availability tables, a form for creating summary plots and access to pregenerated dynamic spectrograms.</Description>
        <Language>en</Language>
      </InformationURL>
      <InformationURL>
        <Name>User's Guide to PWI Receiver Design Features and Modes</Name>
        <URL>http://www-pw.physics.uiowa.edu/plasma-wave/istp/polar/modes.html</URL>
        <Description>Descriptions of PWI receiver and antenna modes.</Description>
        <Language>en</Language>
      </InformationURL>
      <PriorID>spase://VWO/NumericalData/POLAR/PWI/Polar_PWI_MCA_PT1S</PriorID>
      <PriorID>spase://VWO/NumericalData/POLAR/PWI/MCA.PT1.3S</PriorID>
      <PriorID>spase://VSPO/NumericalData/POLAR/PWI/MCA/PT1.3S</PriorID>
    </ResourceHeader>
    <AccessInformation>
      <RepositoryID>spase://SMWG/Repository/NASA/GSFC/SPDF</RepositoryID>
      <Availability>Online</Availability>
      <AccessRights>Open</AccessRights>
      <AccessURL>
        <Name>FTPS from SPDF (not with most browsers)</Name>
        <URL>ftps://spdf.gsfc.nasa.gov/pub/data/polar/pwi/pwi_h0/</URL>
        <Description>FTP access to repository of Polar PWI MCA CDFs at NASA CDAWeb. Name of the data resource: PO_H0_PWI</Description>
        <Language>en</Language>
      </AccessURL>
      <AccessURL>
        <Name>HTTPS from SPDF</Name>
        <URL>https://spdf.gsfc.nasa.gov/pub/data/polar/pwi/pwi_h0/</URL>
        <Description>In CDF via HTTP from SPDF</Description>
      </AccessURL>
      <Format>CDF</Format>
      <Acknowledgement>Users please acknowledge Coordinated Data Analysis Web (CDAWeb) at the NASA Goddard Space Flight Center and Polar PWI instrument Principal Investigator Don Gurnett.</Acknowledgement>
    </AccessInformation>
    <AccessInformation>
      <RepositoryID>spase://SMWG/Repository/NASA/GSFC/SPDF</RepositoryID>
      <Availability>Online</Availability>
      <AccessRights>Open</AccessRights>
      <AccessURL>
        <Name>CDAWeb</Name>
        <URL>https://cdaweb.gsfc.nasa.gov/cgi-bin/eval2.cgi?dataset=PO_H0_PWI&amp;index=sp_phys</URL>
        <ProductKey>PO_H0_PWI</ProductKey>
        <Description>Repository of Polar PWI data with subset, plot and list functionalities from NASA CDAWeb, accessible via web interface. Name of the data resource: PO_H0_PWI.</Description>
        <Language>en</Language>
      </AccessURL>
      <Format>Text</Format>
      <Encoding>None</Encoding>
      <Acknowledgement>Users please acknowledge Coordinated Data Analysis Web (CDAWeb) at the NASA Goddard Space Flight Center and Polar PWI instrument Principal Investigator Don Gurnett.</Acknowledgement>
    </AccessInformation>
    <AccessInformation>
      <RepositoryID>spase://SMWG/Repository/NASA/GSFC/SPDF</RepositoryID>
      <Availability>Online</Availability>
      <AccessRights>Open</AccessRights>
      <AccessURL>
        <Name>CDAWeb HAPI Server</Name>
        <URL>https://cdaweb.gsfc.nasa.gov/hapi</URL>
        <Style>HAPI</Style>
        <ProductKey>PO_H0_PWI@0</ProductKey>
        <ProductKey>PO_H0_PWI@1</ProductKey>
        <Description>Web Service to this product using the HAPI interface.</Description>
      </AccessURL>
      <Format>CSV</Format>
      <Acknowledgement>Users please acknowledge Coordinated Data Analysis Web (CDAWeb) at the NASA Goddard Space Flight Center and Polar PWI instrument Principal Investigator Don Gurnett.</Acknowledgement>
    </AccessInformation>
    <ProcessingLevel>Calibrated</ProcessingLevel>
    <InstrumentID>spase://SMWG/Instrument/POLAR/PWI</InstrumentID>
    <MeasurementType>Waves.Passive</MeasurementType>
    <MeasurementType>Spectrum</MeasurementType>
    <TemporalDescription>
      <TimeSpan>
        <StartDate>1996-03-25T00:00:00Z</StartDate>
        <StopDate>1997-09-16T17:00:00Z</StopDate>
      </TimeSpan>
      <Cadence>PT1.3S</Cadence>
    </TemporalDescription>
    <SpectralRange>RadioFrequency</SpectralRange>
    <ObservedRegion>Earth.Magnetosphere</ObservedRegion>
    <ObservedRegion>Earth.NearSurface.Plasmasphere</ObservedRegion>
    <ObservedRegion>Earth.NearSurface.AuroralRegion</ObservedRegion>
    <ObservedRegion>Earth.NearSurface.PolarCap</ObservedRegion>
    <ObservedRegion>Heliosphere.Inner</ObservedRegion>
    <Caveats>See the Polar Interpretation Issues web site at http://www-pw.physics.uiowa.edu/plasma-wave/istp/polar/interpretation.html</Caveats>
    <!-- Keywords pertaining to the data presentation -->
    <Keyword>Dynamic Spectrogram</Keyword>
    <Keyword>Spectrogram</Keyword>
    <!-- Keywords pertaining to the physical phenomena appearing in spectrograms -->
    <Keyword>AKR</Keyword>
    <Keyword>Auroral hiss</Keyword>
    <Keyword>Auroral Kilometric Radiation</Keyword>
    <Keyword>Banded emissions</Keyword>
    <Keyword>Broadband Electrostatic Noise</Keyword>
    <Keyword>BEN</Keyword>
    <Keyword>Chorus</Keyword>
    <Keyword>Continuum radiation</Keyword>
    <Keyword>Electromagnetic Ion Cyclotron waves</Keyword>
    <Keyword>EMIC</Keyword>
    <Keyword>Electron Cyclotron Harmonics</Keyword>
    <Keyword>Kilometric Continuum radiation</Keyword>
    <Keyword>Myriametric radiation</Keyword>
    <Keyword>Plasmaspheric Hiss</Keyword>
    <Keyword>Solar radio burst</Keyword>
    <Keyword>Terrestrial Kilometric Radiation</Keyword>
    <Keyword>TKR</Keyword>
    <Keyword>UHR</Keyword>
    <Keyword>Upper hybrid resonance</Keyword>
    <Keyword>Whistler mode</Keyword>
    <Keyword>Whistlers</Keyword>
    <Parameter>
      <Name>Time</Name>
      <ParameterKey>Epoch</ParameterKey>
      <Description>Time, begin time of MCA E spectrum</Description>
      <Units>ms</Units>
      <Support>
        <SupportQuantity>Temporal</SupportQuantity>
      </Support>
    </Parameter>
    <Parameter>
      <Name>Time</Name>
      <ParameterKey>EpochB</ParameterKey>
      <Description>Time, begin time of MCA B spectrum</Description>
      <Units>ms</Units>
      <Support>
        <SupportQuantity>Temporal</SupportQuantity>
      </Support>
    </Parameter>
    <Parameter>
      <Name>Electron Cyclotron Frequency</Name>
      <ParameterKey>Fce</ParameterKey>
      <Description>Electron Cyclotron Frequency, scalar</Description>
      <Units>Hz</Units>
      <Support>
        <SupportQuantity>Other</SupportQuantity>
      </Support>
    </Parameter>
    <Parameter>
      <Name>Antenna for MCA E</Name>
      <!-- Parameter Key points to the CDF Variable in the file -->
      <ParameterKey>MCAE_Antenna</ParameterKey>
      <Description>Antenna (MCAE) 0 = Eu, 1 = Ev, 2 = Ez</Description>
      <Units>(0=Eu,1=Ev,2=Ez)</Units>
      <Support>
        <SupportQuantity>Other</SupportQuantity>
      </Support>
    </Parameter>
    <Parameter>
      <Name>Antenna for MCA B</Name>
      <!-- Parameter Key points to the CDF Variable in the file -->
      <ParameterKey>MCAB_Antenna</ParameterKey>
      <Description>Antenna (MCAB) 1 = Bu, 2 = Bv, 3 = Bz</Description>
      <Units>(0=Bu,1=Bv,2=Bz)</Units>
      <Support>
        <SupportQuantity>Other</SupportQuantity>
      </Support>
    </Parameter>
    <Parameter>
      <Name>Time</Name>
      <ParameterKey>Time_PB5</ParameterKey>
      <Description>Time, begin time of spectrum. Contains Year, DOY, MSOD</Description>
      <Support>
        <SupportQuantity>Temporal</SupportQuantity>
      </Support>
    </Parameter>
    <Parameter>
      <Name>Elec. Field MCA E</Name>
      <!-- Parameter Key points to the CDF Variable in the file -->
      <ParameterKey>MCAE_Elec</ParameterKey>
      <Description>Elec. Field at 20 freq., 5.62-311000 Hz (MCA E)</Description>
      <Units>(V/M)**2/Hz</Units>
      <Wave>
        <WaveType>PlasmaWaves</WaveType>
        <WaveQuantity>ACElectricField</WaveQuantity>
        <FrequencyRange>
          <SpectralRange>RadioFrequency</SpectralRange>
          <Low>5.62</Low>
          <High>311000</High>
          <Units>Hz</Units>
        </FrequencyRange>
      </Wave>
    </Parameter>
    <Parameter>
      <Name>Mag. Field MCA B</Name>
      <!-- Parameter Key points to the CDF Variable in the file -->
      <ParameterKey>MCAB_Mag</ParameterKey>
      <Description>Mag. Field at 14 freq., 5.62-10000 Hz (MCA B)</Description>
      <Units>nT**2/Hz</Units>
      <Wave>
        <WaveType>PlasmaWaves</WaveType>
        <WaveQuantity>ACMagneticField</WaveQuantity>
        <FrequencyRange>
          <SpectralRange>RadioFrequency</SpectralRange>
          <Low>5.62</Low>
          <High>10000</High>
          <Units>Hz</Units>
        </FrequencyRange>
      </Wave>
    </Parameter>
    <Parameter>
      <Name>Frequency</Name>
      <!-- Parameter Key points to the CDF Variable in the file -->
      <ParameterKey>Frequency</ParameterKey>
      <Description>Frequencies (E-field), 20 (5.62-311000) Hz</Description>
      <Units>Hz</Units>
      <Support>
        <SupportQuantity>Other</SupportQuantity>
      </Support>
    </Parameter>
    <Parameter>
      <Name>Frequency</Name>
      <!-- Parameter Key points to the CDF Variable in the file -->
      <ParameterKey>FrequencyB</ParameterKey>
      <Description>Frequencies (B-field), 14 (5.62-10000) Hz</Description>
      <Units>Hz</Units>
      <Support>
        <SupportQuantity>Other</SupportQuantity>
      </Support>
    </Parameter>
  </NumericalData>
</Spase>
