{
  "Spase": {
    "xmlns": "http://www.spase-group.org/data/schema",
    "xmlns:xsi": "http://www.w3.org/2001/XMLSchema-instance",
    "xsi:schemaLocation": "http://www.spase-group.org/data/schema http://www.spase-group.org/data/schema/spase-2_4_0.xsd",
    "Version": "2.4.0",
    "NumericalData": {
      "ResourceID": "spase://CNES/NumericalData/CDPP-Archive/DoubleStar1/Ephemeris/DSTAR_SP_T1_AUX",
      "ResourceHeader": {
        "ResourceName": "Double Star 1 Auxiliary Data (Summary Parameters)",
        "DOI": "https://doi.org/10.24400/802406/gmvy-4bgx",
        "ReleaseDate": "2021-11-02T15:44:50Z",
        "Description": "This data set  contains DoubleStar 1 auxiliary data summary parameters.",
        "Contact": {
          "PersonID": "spase://CNES/Person/CDPP-Archive/James.M.James.M.Weygand",
          "Role": "MetadataContact"
        }
      },
      "AccessInformation": {
        "RepositoryID": "spase://CNES/Repository/CDPP-Archive/REGARDS-CDPP",
        "Availability": "Online",
        "AccessURL": {
          "Name": "REGARDS",
          "URL": "https://cdpp-archive.cnes.fr"
        },
        "Format": "CDF"
      },
      "InstrumentID": "spase://CNES/Instrument/CDPP-Archive/DoubleStar1/Ephemeris",
      "MeasurementType": "Ephemeris",
      "TemporalDescription": {
        "TimeSpan": {
          "StartDate": "2004-01-03T00:00:00Z",
          "StopDate": "2007-09-19T00:00:00Z"
        }
      },
      "ObservedRegion": [
        "Earth.Magnetosphere",
        "Earth.Magnetosphere.Magnetotail",
        "Earth.Magnetosphere.Main",
        "Earth.Magnetosphere.RadiationBelt",
        "Earth.NearSurface.Ionosphere",
        "Earth.NearSurface.Plasmasphere"
      ],
      "Parameter": [
        {
          "Name": "Double Star 1 SC Orbit Number",
          "Support": {
            "SupportQuantity": "Other"
          }
        },
        {
          "Name": "Double Star 1 Reference SC Position GSE",
          "Description": "Double Star 1 Position, in GSE, of the  Spacecraft.",
          "Units": "km",
          "CoordinateSystem": {
            "CoordinateRepresentation": "Cartesian",
            "CoordinateSystemName": "GSE"
          },
          "Support": {
            "SupportQuantity": "Positional"
          }
        },
        {
          "Name": "Double Star 1 Reference SC Velocity GSE",
          "Description": "Double Star 1 Velocity, in GSE, of the  Spacecraft.",
          "Units": "km/s",
          "CoordinateSystem": {
            "CoordinateRepresentation": "Cartesian",
            "CoordinateSystemName": "GSE"
          },
          "Support": {
            "SupportQuantity": "Velocity"
          }
        },
        {
          "Name": "Double Star 1 GSE latitude of SC spin axis",
          "Description": "Double Star 1 GSE latitude of the Spacecraft  spin axis",
          "Units": "째",
          "UnitsConversion": "0.0174532925>rad",
          "Support": {
            "SupportQuantity": "Other"
          }
        },
        {
          "Name": "Double Star 1 GSE longitude of SC spin axis",
          "Description": "Double Star 1 GSE longitude of the Spacecraft  spin axis",
          "Units": "째",
          "UnitsConversion": "0.0174532925>rad",
          "Support": {
            "SupportQuantity": "Other"
          }
        },
        {
          "Name": "Double Star 1  Rotation angle GSE to GSM",
          "Description": "Rotation angle GSE to GSM",
          "Units": "째",
          "UnitsConversion": "0.0174532925>rad",
          "Support": {
            "SupportQuantity": "Other"
          }
        },
        {
          "Name": "Double Star 1  Dipole tilt in GSM z-x plane",
          "Description": "Dipole tilt in GSM z-x plane",
          "Units": "째",
          "UnitsConversion": "0.0174532925>rad",
          "Support": {
            "SupportQuantity": "Other"
          }
        }
      ]
    }
  }
}