<?xml version="1.0" encoding="UTF-8" standalone="yes"?>
<Spase xmlns="http://www.spase-group.org/data/schema" xmlns:xsi="http://www.w3.org/2001/XMLSchema-instance" xsi:schemaLocation="http://www.spase-group.org/data/schema http://www.spase-group.org/data/schema/spase-2_4_0.xsd">
  <Version>2.4.0</Version>
  <NumericalData>
    <ResourceID>spase://CNES/NumericalData/CDPP-Archive/DoubleStar2/LFEW/DSTAR_PP_T2_LFE</ResourceID>
    <ResourceHeader>
      <ResourceName>Double Star 2 LFEW Prime Parameters</ResourceName>
      <DOI>https://doi.org/10.24400/802406/21fg-hb5h</DOI>
      <ReleaseDate>2021-11-02T15:44:52Z</ReleaseDate>
      <Description>The Low Frequency Electromagnetic Wave Detector (LFEW) is a search-coil type three-component electromagnetic wave detector, with a frequency range from 8 Hz to 10 kHz in three frequency segments (8－100 Hz, 100－1000 Hz, and 1－10 kHz). It is designed to measure low frequency magnetic waves in different regions of the magnetosphere.

This data set contains Double Star 2 LFEW prime parameters at spin resolution  including the instrument status and  the components of the wave spectral density parallel and perpendicular to the magnetic field in three frequency bands each.</Description>
      <Contact>
        <PersonID>spase://CNES/Person/CDPP-Archive/Jinbin.Cao</PersonID>
        <Role>PrincipalInvestigator</Role>
      </Contact>
    </ResourceHeader>
    <AccessInformation>
      <RepositoryID>spase://CNES/Repository/CDPP-Archive/REGARDS-CDPP</RepositoryID>
      <Availability>Online</Availability>
      <AccessURL>
        <Name>REGARDS</Name>
        <URL>https://cdpp-archive.cnes.fr</URL>
      </AccessURL>
      <Format>CDF</Format>
    </AccessInformation>
    <ProcessingLevel>Calibrated</ProcessingLevel>
    <InstrumentID>spase://CNES/Instrument/CDPP-Archive/DoubleStar2/LFEW</InstrumentID>
    <MeasurementType>MagneticField</MeasurementType>
    <MeasurementType>InstrumentStatus</MeasurementType>
    <TemporalDescription>
      <TimeSpan>
        <StartDate>2004-05-15T00:00:00Z</StartDate>
        <StopDate>2006-10-30T00:00:00Z</StopDate>
      </TimeSpan>
    </TemporalDescription>
    <ObservedRegion>Earth.Magnetosphere</ObservedRegion>
    <ObservedRegion>Earth.Magnetosphere.Magnetotail</ObservedRegion>
    <ObservedRegion>Earth.Magnetosphere.Main</ObservedRegion>
    <ObservedRegion>Earth.Magnetosphere.RadiationBelt</ObservedRegion>
    <ObservedRegion>Earth.NearSurface.Ionosphere</ObservedRegion>
    <ObservedRegion>Earth.NearSurface.Plasmasphere</ObservedRegion>
    <Parameter>
      <Name>Double Star 2 LFEW Magnetic field Power spectral density parallel to B0 (8 - 100 Hz) Prime Parameter</Name>
      <Description>Double Star 2 LFEW Magnetic field Power spectral density parallel to B0   (8 - 100 Hz)  Prime Parameter</Description>
      <Units>nT^2 Hz^-1</Units>
      <Field>
        <Qualifier>Scalar</Qualifier>
        <FieldQuantity>Magnetic</FieldQuantity>
        <FrequencyRange>
          <Low>8</Low>
          <High>100</High>
          <Units>Hz</Units>
        </FrequencyRange>
      </Field>
    </Parameter>
    <Parameter>
      <Name>Double Star 2 LFEW Magnetic field Power spectral density parallel to B0 (100 - 1000 Hz) Prime Parameter</Name>
      <Description>Double Star 2 LFEW Magnetic field Power spectral density parallel to B0 (100 - 1000 Hz) Prime Parameter</Description>
      <Units>nT^2 Hz^-1</Units>
      <Field>
        <Qualifier>Scalar</Qualifier>
        <FieldQuantity>Magnetic</FieldQuantity>
        <FrequencyRange>
          <Low>100</Low>
          <High>1000</High>
          <Units>Hz</Units>
        </FrequencyRange>
      </Field>
    </Parameter>
    <Parameter>
      <Name>Double Star 2 LFEW Magnetic field Power spectral density parallel to B0 (1000 - 10000 Hz) Prime Parameter</Name>
      <Description>Double Star 2 LFEW Magnetic field Power spectral density parallel to B0 (1000 - 10000 Hz) Prime Parameter</Description>
      <Units>nT^2 Hz^-1</Units>
      <Field>
        <Qualifier>Scalar</Qualifier>
        <FieldQuantity>Magnetic</FieldQuantity>
        <FrequencyRange>
          <Low>1000</Low>
          <High>10000</High>
          <Units>Hz</Units>
        </FrequencyRange>
      </Field>
    </Parameter>
    <Parameter>
      <Name>Double Star 2 LFEW Magnetic field Power spectral density Perpendicular to B0 (8 - 100 Hz) Prime Parameter</Name>
      <Description>Double Star 2 LFEW Magnetic field Power spectral density Perpendicular to B0   (8 - 100 Hz)  Prime Parameter</Description>
      <Units>nT^2 Hz^-1</Units>
      <Field>
        <Qualifier>Scalar</Qualifier>
        <FieldQuantity>Magnetic</FieldQuantity>
        <FrequencyRange>
          <Low>8</Low>
          <High>100</High>
          <Units>Hz</Units>
        </FrequencyRange>
      </Field>
    </Parameter>
    <Parameter>
      <Name>Double Star 2 LFEW Magnetic field Power spectral density Perpendicular to B0 (100 - 1000 Hz) Prime Parameter</Name>
      <Description>Double Star 2 LFEW Magnetic field Power spectral density Perpendicular to B0 (100 - 1000 Hz) Prime Parameter</Description>
      <Units>nT^2 Hz^-1</Units>
      <Field>
        <Qualifier>Scalar</Qualifier>
        <FieldQuantity>Magnetic</FieldQuantity>
        <FrequencyRange>
          <Low>100</Low>
          <High>1000</High>
          <Units>Hz</Units>
        </FrequencyRange>
      </Field>
    </Parameter>
    <Parameter>
      <Name>Double Star 2 LFEW Magnetic field Power spectral density Perpendicular to B0 (1000 - 10000 Hz) Prime Parameter</Name>
      <Description>Double Star 2 LFEW Magnetic field Power spectral density Perpendicular to B0 (1000 - 10000 Hz) Prime Parameter</Description>
      <Units>nT^2 Hz^-1</Units>
      <Field>
        <Qualifier>Scalar</Qualifier>
        <FieldQuantity>Magnetic</FieldQuantity>
        <FrequencyRange>
          <Low>1000</Low>
          <High>10000</High>
          <Units>Hz</Units>
        </FrequencyRange>
      </Field>
    </Parameter>
    <Parameter>
      <Name>Double Star 2 LFEW Instrument Status</Name>
      <Description>Double Star 2 LFEW Instrument Status</Description>
      <Support>
        <SupportQuantity>Other</SupportQuantity>
      </Support>
    </Parameter>
  </NumericalData>
</Spase>
